llama_index/readers/make_com/__init__.py
llama_index/readers/make_com/base.py
llama_index_readers_make_com-0.4.1.dist-info/METADATA
llama_index_readers_make_com-0.4.1.dist-info/WHEEL
llama_index_readers_make_com-0.4.1.dist-info/licenses/LICENSE
llama_index_readers_make_com-0.4.1.dist-info/RECORD
